hitchstory/__init__.py
hitchstory/arguments.py
hitchstory/doc_template.py
hitchstory/docstory.py
hitchstory/engine.py
hitchstory/exceptions.py
hitchstory/given.py
hitchstory/matchers.py
hitchstory/result.py
hitchstory/step_method.py
hitchstory/story.py
hitchstory/story_collection.py
hitchstory/story_file.py
hitchstory/story_list.py
hitchstory/story_step.py
hitchstory/utils.py
hitchstory/templates/failure.jinja2
hitchstory/templates/multiple.jinja2
hitchstory/templates/stacktrace_default.jinja2
hitchstory/templates/success.jinja2
hitchstory-0.24.2.dist-info/licenses/LICENSE.txt
hitchstory-0.24.2.dist-info/METADATA
hitchstory-0.24.2.dist-info/WHEEL
hitchstory-0.24.2.dist-info/top_level.txt
hitchstory-0.24.2.dist-info/RECORD
