Metadata-Version: 2.4
Name: hitchstory
Version: 0.24.2
Summary: Type-safe YAML-based example specification driven development framework for python.
Author-email: Colm O'Connor <colm.oconnor.github@gmail.com>
License: Elastic License 2.0
Project-URL: homepage, https://hitchdev.com/hitchstory
Project-URL: documentation, https://hitchdev.com/hitchstory/using
Project-URL: repository, https://github.com/hitchdev/hitchstory
Project-URL: changelog, https://hitchdev.com/hitchstory/changelog
Keywords: yaml,hitchdev,bdd,tdd,testing,tests
Classifier: Programming Language :: Python :: 3
Classifier: Topic :: Software Development :: Quality Assurance
Classifier: Topic :: Software Development :: Testing
Classifier: Topic :: Text Processing :: Markup
Classifier: Topic :: Software Development :: Libraries
Classifier: Natural Language :: English
Classifier: Environment :: Console
Requires-Python: >=3.7.0
License-File: LICENSE.txt
Requires-Dist: strictyaml>=1.4.3
Requires-Dist: path.py>=9.0
Requires-Dist: jinja2>=2.9
Requires-Dist: colorama>=0.3.8
Requires-Dist: python-slugify>=1.2.1
Requires-Dist: prettystack>=0.3.0
Requires-Dist: psutil>=5.0.0
Requires-Dist: mergedeep>=1.2.0
Requires-Dist: click>=7.1.2
Dynamic: license-file
